graphi_crud/__init__.py
graphi_crud/create_mutation.py
graphi_crud/delete_mutation.py
graphi_crud/filters.py
graphi_crud/graphi_types.py
graphi_crud/mutations.py
graphi_crud/queries.py
graphi_crud/update_mutation.py
graphi_crud-1.2.3.3.dist-info/LICENCE
graphi_crud-1.2.3.3.dist-info/METADATA
graphi_crud-1.2.3.3.dist-info/WHEEL
graphi_crud-1.2.3.3.dist-info/RECORD
